plugins/CoreTypes.py
plugins/PluginManager.py
plugins/__init__.py
plugins/py.typed
plugins/common/ElementTreeData.py
plugins/common/LinkMakerMixin.py
plugins/common/PluginTypes.py
plugins/common/__init__.py
plugins/common/py.typed
plugins/common/ui/BaseDlgEdit.py
plugins/common/ui/Dimensions.py
plugins/common/ui/DimensionsContainer.py
plugins/common/ui/DualSpinnerContainer.py
plugins/common/ui/__init__.py
plugins/common/ui/py.typed
plugins/coreinterfaces/BasePluginInterface.py
plugins/coreinterfaces/IOPluginInterface.py
plugins/coreinterfaces/IPluginAdapter.py
plugins/coreinterfaces/Singleton.py
plugins/coreinterfaces/ToolPluginInterface.py
plugins/coreinterfaces/__init__.py
plugins/coreinterfaces/py.typed
plugins/exceptions/AbstractMethodNotImplementedException.py
plugins/exceptions/InvalidPluginExtensionException.py
plugins/exceptions/InvalidPluginNameException.py
plugins/exceptions/__init__.py
plugins/exceptions/py.typed
plugins/ioplugins/IOAscii.py
plugins/ioplugins/IODTD.py
plugins/ioplugins/IOGML.py
plugins/ioplugins/IOJava.py
plugins/ioplugins/IOPdf.py
plugins/ioplugins/IOPython.py
plugins/ioplugins/IOWxImage.py
plugins/ioplugins/IOXml.py
plugins/ioplugins/__init__.py
plugins/ioplugins/py.typed
plugins/ioplugins/dtd/DTDAttribute.py
plugins/ioplugins/dtd/DTDElementTypes.py
plugins/ioplugins/dtd/DTDParser.py
plugins/ioplugins/dtd/__init__.py
plugins/ioplugins/dtd/py.typed
plugins/ioplugins/gml/GMLExporter.py
plugins/ioplugins/gml/UnsupportedOperation.py
plugins/ioplugins/gml/__init__.py
plugins/ioplugins/gml/py.typed
plugins/ioplugins/java/JavaReader.py
plugins/ioplugins/java/JavaWriter.py
plugins/ioplugins/java/__init__.py
plugins/ioplugins/java/py.typed
plugins/ioplugins/pdf/ImageFormat.py
plugins/ioplugins/pdf/ImageOptions.py
plugins/ioplugins/pdf/OglToPyUmlDefinition.py
plugins/ioplugins/pdf/__init__.py
plugins/ioplugins/python/Python3LexerBase.py
plugins/ioplugins/python/Python3ParserBase.py
plugins/ioplugins/python/PythonParseException.py
pyutplugincore-0.6.5.dist-info/LICENSE
pyutplugincore-0.6.5.dist-info/METADATA
pyutplugincore-0.6.5.dist-info/WHEEL
pyutplugincore-0.6.5.dist-info/top_level.txt
pyutplugincore-0.6.5.dist-info/RECORD
