Metadata-Version: 2.1
Name: pyutplugincore
Version: 0.6.5
Summary: Pyut Plugins
Home-page: https://github.com/hasii2011/pyutplugincore
Author: Humberto A. Sanchez II
Author-email: humberto.a.sanchez.ii@gmail.com
Maintainer: Humberto A. Sanchez II
Maintainer-email: humberto.a.sanchez.ii@gmail.com
License-File: LICENSE
Requires-Dist: click (~=8.1.3)
Requires-Dist: antlr4-python3-runtime (==4.11.1)
Requires-Dist: pyumldiagrams (==2.30.8)
Requires-Dist: networkx (==2.8.5)
Requires-Dist: orthogonal (==1.1.7)
Requires-Dist: wxPython (~=4.2.0)
Requires-Dist: pyutmodel (==1.3.3)
Requires-Dist: ogl (==0.60.25)
Requires-Dist: untanglepyut (==0.6.5)
Requires-Dist: oglio (==0.5.40)
